{
    "coord": {
        "lon": -56.0967,
        "lat": -15.5961
    },
    "weather": [
        {
            "id": 800,
            "main": "Clear",
            "description": "céu limpo",
            "icon": "01n"
        }
    ],
    "base": "stations",
    "main": {
        "temp": 24.96,
        "feels_like": 25.42,
        "temp_min": 24.96,
        "temp_max": 24.96,
        "pressure": 1013,
        "humidity": 73,
        "sea_level": 1013,
        "grnd_level": 991
    },
    "visibility": 10000,
    "wind": {
        "speed": 1.03,
        "deg": 80
    },
    "clouds": {
        "all": 0
    },
    "dt": 1748213966,
    "sys": {
        "type": 1,
        "id": 8352,
        "country": "BR",
        "sunrise": 1748167345,
        "sunset": 1748208037
    },
    "timezone": -14400,
    "id": 3465038,
    "name": "Cuiabá",
    "cod": 200
}