{
    "coord": {
        "lon": -38.5108,
        "lat": -12.9711
    },
    "weather": [
        {
            "id": 803,
            "main": "Clouds",
            "description": "nuvens quebradas",
            "icon": "04d"
        }
    ],
    "base": "stations",
    "main": {
        "temp": 25.98,
        "feels_like": 25.98,
        "temp_min": 25.98,
        "temp_max": 25.98,
        "pressure": 1016,
        "humidity": 79,
        "sea_level": 1016,
        "grnd_level": 1016
    },
    "visibility": 10000,
    "wind": {
        "speed": 5.06,
        "deg": 180,
        "gust": 5.11
    },
    "clouds": {
        "all": 68
    },
    "dt": 1748455487,
    "sys": {
        "type": 1,
        "id": 8454,
        "country": "BR",
        "sunrise": 1748422120,
        "sunset": 1748463262
    },
    "timezone": -10800,
    "id": 3450554,
    "name": "Salvador",
    "cod": 200
}